web3dex/__init__.py
web3dex/avalance.py
web3dex/bsc.py
web3dex/cronos.py
web3dex/dex.py
web3dex/ethereum.py
web3dex/fantom.py
web3dex/moonbeam.py
web3dex/moonriver.py
web3dex/polygon.py
web3dex/abi/beamswap_factory_abi.json
web3dex/abi/knightswap_factory_abi.json
web3dex/abi/pancakeswap_factory_abi.json
web3dex/abi/pancakeswap_router_abi.json
web3dex/abi/pangolin_router_abi.json
web3dex/abi/solidex_factory_abi.json
web3dex/abi/solidex_router_abi.json
web3dex/abi/solidly_factory_abi.json
web3dex/abi/solidly_router_abi.json
web3dex/abi/spookyswap_factory_abi.json
web3dex/abi/stellaswap_router_abi.json
web3dex/abi/token_abi.json
web3dex/abi/traderjoe_router_abi.json
web3dex/abi/uniswapv2_factory_abi.json
web3dex/abi/uniswapv2_liquidity_abi.json
web3dex/abi/uniswapv2_router_abi.json
web3dex/abi/zenlink_factory_abi.json
web3dex/abi/zenlink_liquidity_abi.json
web3dex/abi/zenlink_router_abi.json
web3dex/configs/avalance/pangolin.json
web3dex/configs/avalance/sushiswap.json
web3dex/configs/avalance/thorus.json
web3dex/configs/avalance/traderjoe.json
web3dex/configs/bsc/apeswap.json
web3dex/configs/bsc/babyswap.json
web3dex/configs/bsc/biswap.json
web3dex/configs/bsc/knightswap.json
web3dex/configs/bsc/mdexswap.json
web3dex/configs/bsc/pancakeswap.json
web3dex/configs/bsc/pinkswap.json
web3dex/configs/bsc/safemoon.json
web3dex/configs/cronos/mmfinance.json
web3dex/configs/cronos/vvsfinance.json
web3dex/configs/ethereum/shibaswap.json
web3dex/configs/ethereum/stepn.json
web3dex/configs/ethereum/sushiswap.json
web3dex/configs/ethereum/uniswap.json
web3dex/configs/fantom/solidex.json
web3dex/configs/fantom/solidly.json
web3dex/configs/fantom/spiritswap.json
web3dex/configs/fantom/spookyswap.json
web3dex/configs/moonbeam/beamswap.json
web3dex/configs/moonbeam/padswap.json
web3dex/configs/moonbeam/solarflare.json
web3dex/configs/moonbeam/stellaswap.json
web3dex/configs/moonbeam/thorus.json
web3dex/configs/moonbeam/zenlink.json
web3dex/configs/moonriver/solarbeam.json
web3dex-0.0.1.dist-info/LICENSE
web3dex-0.0.1.dist-info/METADATA
web3dex-0.0.1.dist-info/WHEEL
web3dex-0.0.1.dist-info/top_level.txt
web3dex-0.0.1.dist-info/RECORD
