Metadata-Version: 2.1
Name: web3dex
Version: 0.0.1
Summary: A flexible python library to interact with evm-like DEX.
Home-page: https://github.com/0xfffangel/web3dex-python
Author: 0xfffangel
Author-email: 0xfffangel@protonmail.com
Project-URL: Bug Tracker, https://github.com/0xfffangel/web3dex-python/issues
Classifier: Programming Language :: Python :: 3
Classifier: License :: OSI Approved :: MIT License
Classifier: Operating System :: OS Independent
Requires-Python: >=3.6
License-File: LICENSE
Requires-Dist: web3 (>=5.27.0)
